setup.cfg
setup.py
django_fastcgi/__init__.py
django_fastcgi/servers/__init__.py
django_fastcgi/servers/fastcgi.py
django_fastcgi/utils/__init__.py
django_fastcgi/utils/demonize.py
django_fastcgi/utils/six.py
django_fastcgi_server.egg-info/PKG-INFO
django_fastcgi_server.egg-info/SOURCES.txt
django_fastcgi_server.egg-info/dependency_links.txt
django_fastcgi_server.egg-info/top_level.txt