Metadata-Version: 1.1
Name: django-fastcgi-server
Version: 0.1
Summary: Package for deploying django projects via FastCGI for django version 1.9 or higher.
Home-page: https://github.com/NetAngels/django-fastcgi
Author: NetAngels team
Author-email: info@netangels.ru
License: UNKNOWN
Download-URL: https://github.com/NetAngels/django-fastcgi/tarball/0.1
Keywords: django fastcgi
Platform: UNKNOWN
